README.md
setup.py
TOPSIS_Khushleen_101803162.egg-info/PKG-INFO
TOPSIS_Khushleen_101803162.egg-info/SOURCES.txt
TOPSIS_Khushleen_101803162.egg-info/dependency_links.txt
TOPSIS_Khushleen_101803162.egg-info/requires.txt
TOPSIS_Khushleen_101803162.egg-info/top_level.txt
topsis_analysis/__init__.py
topsis_analysis/topsispackage.py