Metadata-Version: 2.1
Name: TOPSIS-Khushleen-101803162
Version: 0.3.0
Summary: This package can be used to calculate the topsis score of multiple component data and rank them accordingly
Home-page: UNKNOWN
Author: Khushleen Billing
Author-email: khushleenbilling21@gmail.com
License: MIT
Keywords: TOPSIS
Platform: UNKNOWN
Classifier: Development Status :: 3 - Alpha
Classifier: Intended Audience :: Developers
Classifier: Topic :: Software Development :: Build Tools
Classifier: License :: OSI Approved :: MIT License
Classifier: Programming Language :: Python :: 3
Classifier: Programming Language :: Python :: 3.4
Classifier: Programming Language :: Python :: 3.5
Classifier: Programming Language :: Python :: 3.6
